Workbook

Sheet current_products_edited
A1: Product No. | B1: ProductName | C1: Company No. | D1: Registration Status | E1: Appl No. | F1: Appl Status | G1: Auth Type | H1: Received Date | I1: Reviewer | J1: PRODUCT TYPE | K1: is_PDF_downloaded | L1: sub | M1: concat | N1: lookip | O1: isdownloaded2 | P1: =COUNTIF(N:N,"FALSE") -> 672
A2: 100-1098 | B2: QUADRIS FLOWABLE FUNGICIDE (2EE - DOWNY MILDEW) | C2: 00COR | D2: REGISTERED | E2: 15982 | F2: CLOSED | G2: 2EE | H2: 40036 | J2: FUNGICIDE | K2: TRUE | L2: =SUBSTITUTE(LOWER(SUBSTITUTE(SUBSTITUTE(SUBSTITUTE(B2," ",""),"/",""),"&","")),"and","") -> quadrisflowablefungicide(2ee-downymildew) | M2: =_xlfn.CONCAT(L2,A2) -> quadrisflowablefungicide(2ee-downymildew)100-1098 | N2: =IFERROR(VLOOKUP(LOWER(M2),file_list!$B:$B,1,FALSE),FALSE) -> quadrisflowablefungicide(2ee-downymildew)100-1098 | O2: =IF(N2=FALSE,"FALSE","TRUE") -> TRUE
A3: 264-827 | B3: ADMIRE PRO SYSTEMIC PROTECTANT (2EE - SWEDE MIDGE) | C3: 00COR | D3: REGISTERED | E3: 14441 | F3: CLOSED | G3: 2EE | H3: 39864 | J3: INSECTICIDE | K3: TRUE | L3: =SUBSTITUTE(LOWER(SUBSTITUTE(SUBSTITUTE(SUBSTITUTE(B3," ",""),"/",""),"&","")),"and","") -> admireprosystemicprotectant(2ee-swedemidge) | M3: =_xlfn.CONCAT(L3,A3) -> admireprosystemicprotectant(2ee-swedemidge)264-827 | N3: =IFERROR(VLOOKUP(LOWER(M3),file_list!$B:$B,1,FALSE),FALSE) -> admireprosystemicprotectant(2ee-swedemidge)264-827 | O3: =IF(N3=FALSE,"FALSE","TRUE") -> TRUE
A4: 55146-64 | B4: CHAMP FORMULA 2 FLOWABLE [UNRESTRICTED AS OF 9/21/2005] (2EE - PHYTOPHORA BLIGHT IN PEPPER) | C4: 00COR | D4: REGISTERED | E4: 5681 | F4: CLOSED | G4: 2EE | H4: 38903 | J4: FUNGICIDE | K4: FALSE | L4: =SUBSTITUTE(LOWER(SUBSTITUTE(SUBSTITUTE(SUBSTITUTE(B4," ",""),"/",""),"&","")),"and","") -> champformula2flowable[unrestrictedasof9212005](2ee-phytophorablightinpepper) | M4: =_xlfn.CONCAT(L4,A4) -> champformula2flowable[unrestrictedasof9212005](2ee-phytophorablightinpepper)55146-64 | N4: =IFERROR(VLOOKUP(LOWER(M4),file_list!$B:$B,1,FALSE),FALSE) -> champformula2flowable[unrestrictedasof9212005](2ee-phytophorablightinpepper)55146-64 | O4: =IF(N4=FALSE,"FALSE","TRUE") -> TRUE
A5: 55146-64 | B5: CHAMP FORMULA 2 FLOWABLE (2EE - PHYTOPHTHORA BLIGHT IN CUCURBIT) | C5: 00COR | D5: REGISTERED | E5: 4999 | F5: CLOSED | G5: 2EE | H5: 38817 | J5: FUNGICIDE | K5: TRUE | L5: =SUBSTITUTE(LOWER(SUBSTITUTE(SUBSTITUTE(SUBSTITUTE(B5," ",""),"/",""),"&","")),"and","") -> champformula2flowable(2ee-phytophthorablightincucurbit) | M5: =_xlfn.CONCAT(L5,A5) -> champformula2flowable(2ee-phytophthorablightincucurbit)55146-64 | N5: =IFERROR(VLOOKUP(LOWER(M5),file_list!$B:$B,1,FALSE),FALSE) -> champformula2flowable(2ee-phytophthorablightincucurbit)55146-64 | O5: =IF(N5=FALSE,"FALSE","TRUE") -> TRUE
A6: 100-1295 | B6: WARRIOR II WITH ZEON TECHNOLOGY (25 FOOT BUFFER STRIP TO COASTAL MARSHES) (2EE - LEEK MOTH) | C6: 00USDA | D6: REGISTERED | E6: 19181 | F6: CLOSED | G6: 2EE | H6: 40367 | J6: INSECTICIDE | K6: TRUE | L6: =SUBSTITUTE(LOWER(SUBSTITUTE(SUBSTITUTE(SUBSTITUTE(B6," ",""),"/",""),"&","")),"and","") -> warrioriiwithzeontechnology(25footbufferstriptocoastalmarshes)(2ee-leekmoth) | M6: =_xlfn.CONCAT(L6,A6) -> warrioriiwithzeontechnology(25footbufferstriptocoastalmarshes)(2ee-leekmoth)100-1295 | N6: =IFERROR(VLOOKUP(LOWER(M6),file_list!$B:$B,1,FALSE),FALSE) -> warrioriiwithzeontechnology(25footbufferstriptocoastalmarshes)(2ee-leekmoth)100-1295 | O6: =IF(N6=FALSE,"FALSE","TRUE") -> TRUE
A7: 352-384 | B7: DUPONT LANNATE LV INSECTICIDE (2EE - LEEK MOTH) | C7: 00USDA | D7: REGISTERED | E7: 19181 | F7: CLOSED | G7: 2EE | H7: 40367 | J7: INSECTICIDE | K7: TRUE | L7: =SUBSTITUTE(LOWER(SUBSTITUTE(SUBSTITUTE(SUBSTITUTE(B7," ",""),"/",""),"&","")),"and","") -> dupontlannatelvinsecticide(2ee-leekmoth) | M7: =_xlfn.CONCAT(L7,A7) -> dupontlannatelvinsecticide(2ee-leekmoth)352-384 | N7: =IFERROR(VLOOKUP(LOWER(M7),file_list!$B:$B,1,FALSE),FALSE) -> dupontlannatelvinsecticide(2ee-leekmoth)352-384 | O7: =IF(N7=FALSE,"FALSE","TRUE") -> TRUE
A8: 62719-282 | B8: ENTRUST (2EE - LEEK MOTH) | C8: 00USDA | D8: REGISTERED | E8: 19181 | F8: CLOSED | G8: 2EE | H8: 40367 | J8: INSECTICIDE | K8: TRUE | L8: =SUBSTITUTE(LOWER(SUBSTITUTE(SUBSTITUTE(SUBSTITUTE(B8," ",""),"/",""),"&","")),"and","") -> entrust(2ee-leekmoth) | M8: =_xlfn.CONCAT(L8,A8) -> entrust(2ee-leekmoth)62719-282 | N8: =IFERROR(VLOOKUP(LOWER(M8),file_list!$B:$B,1,FALSE),FALSE) -> entrust(2ee-leekmoth)62719-282 | O8: =IF(N8=FALSE,"FALSE","TRUE") -> TRUE
A9: 62719-545 | B9: RADIANT SC (2EE - LEEK MOTH) | C9: 00USDA | D9: REGISTERED | E9: 19181 | F9: CLOSED | G9: 2EE | H9: 40367 | J9: INSECTICIDE | K9: TRUE | L9: =SUBSTITUTE(LOWER(SUBSTITUTE(SUBSTITUTE(SUBSTITUTE(B9," ",""),"/",""),"&","")),"and","") -> radiantsc(2ee-leekmoth) | M9: =_xlfn.CONCAT(L9,A9) -> radiantsc(2ee-leekmoth)62719-545 | N9: =IFERROR(VLOOKUP(LOWER(M9),file_list!$B:$B,1,FALSE),FALSE) -> radiantsc(2ee-leekmoth)62719-545 | O9: =IF(N9=FALSE,"FALSE","TRUE") -> TRUE
A10: 73049-39 | B10: DIPEL DF DRY FLOWABLE BIOLOGICAL INSECTICIDE (2EE - LEEK MOTH) | C10: 00USDA | D10: REGISTERED | E10: 19181 | F10: CLOSED | G10: 2EE | H10: 40367 | J10: INSECTICIDE | K10: TRUE | L10: =SUBSTITUTE(LOWER(SUBSTITUTE(SUBSTITUTE(SUBSTITUTE(B10," ",""),"/",""),"&","")),"and","") -> dipeldfdryflowablebiologicalinsecticide(2ee-leekmoth) | M10: =_xlfn.CONCAT(L10,A10) -> dipeldfdryflowablebiologicalinsecticide(2ee-leekmoth)73049-39 | N10: =IFERROR(VLOOKUP(LOWER(M10),file_list!$B:$B,1,FALSE),FALSE) -> dipeldfdryflowablebiologicalinsecticide(2ee-leekmoth)73049-39 | O10: =IF(N10=FALSE,"FALSE","TRUE") -> TRUE
A11: 100-1000 | B11: DEMON WP INSECTICIDE IN WATER SOLUBLE PACKETS | C11: 100 | D11: REGISTERED | E11: 1288082 | F11: CLOSED | G11: ROUTINE | H11: 45604 | I11: KATHERINE HETTER | J11: INSECTICIDE | K11: TRUE | L11: =SUBSTITUTE(LOWER(SUBSTITUTE(SUBSTITUTE(SUBSTITUTE(B11," ",""),"/",""),"&","")),"and","") -> demonwpinsecticideinwatersolublepackets | M11: =_xlfn.CONCAT(L11,A11) -> demonwpinsecticideinwatersolublepackets100-1000 | N11: =IFERROR(VLOOKUP(LOWER(M11),file_list!$B:$B,1,FALSE),FALSE) -> demonwpinsecticideinwatersolublepackets100-1000 | O11: =IF(N11=FALSE,"FALSE","TRUE") -> TRUE
A12: 100-1014 | B12: TRIMMIT 2SC PLANT GROWTH REGULATOR | C12: 100 | D12: REGISTERED | E12: 1288082 | F12: CLOSED | G12: ROUTINE | H12: 45604 | I12: KATHERINE HETTER | J12: GROWTH REGULATOR | K12: TRUE | L12: =SUBSTITUTE(LOWER(SUBSTITUTE(SUBSTITUTE(SUBSTITUTE(B12," ",""),"/",""),"&","")),"and","") -> trimmit2scplantgrowthregulator | M12: =_xlfn.CONCAT(L12,A12) -> trimmit2scplantgrowthregulator100-1014 | N12: =IFERROR(VLOOKUP(LOWER(M12),file_list!$B:$B,1,FALSE),FALSE) -> trimmit2scplantgrowthregulator100-1014 | O12: =IF(N12=FALSE,"FALSE","TRUE") -> TRUE
A13: 100-1050 | B13: TALON-G RODENTICIDE BAIT PACK MINI-PELLETS CONTAINS BITREX | C13: 100 | D13: REGISTERED | E13: 1288082 | F13: CLOSED | G13: ROUTINE | H13: 45604 | I13: KATHERINE HETTER | J13: RODENTICIDE | K13: TRUE | L13: =SUBSTITUTE(LOWER(SUBSTITUTE(SUBSTITUTE(SUBSTITUTE(B13," ",""),"/",""),"&","")),"and","") -> talon-grodenticidebaitpackmini-pelletscontainsbitrex | M13: =_xlfn.CONCAT(L13,A13) -> talon-grodenticidebaitpackmini-pelletscontainsbitrex100-1050 | N13: =IFERROR(VLOOKUP(LOWER(M13),file_list!$B:$B,1,FALSE),FALSE) -> talon-grodenticidebaitpackmini-pelletscontainsbitrex100-1050 | O13: =IF(N13=FALSE,"FALSE","TRUE") -> TRUE
A14: 100-1055 | B14: TALON WEATHERBLOK XT | C14: 100 | D14: REGISTERED | E14: 1288082 | F14: CLOSED | G14: ROUTINE | H14: 45604 | I14: KATHERINE HETTER | J14: RODENTICIDE | K14: TRUE | L14: =SUBSTITUTE(LOWER(SUBSTITUTE(SUBSTITUTE(SUBSTITUTE(B14," ",""),"/",""),"&","")),"and","") -> talonweatherblokxt | M14: =_xlfn.CONCAT(L14,A14) -> talonweatherblokxt100-1055 | N14: =IFERROR(VLOOKUP(LOWER(M14),file_list!$B:$B,1,FALSE),FALSE) -> talonweatherblokxt100-1055 | O14: =IF(N14=FALSE,"FALSE","TRUE") -> TRUE
A15: 100-1061 | B15: REGLONE DESICCANT | C15: 100 | D15: REGISTERED | E15: 1288082 | F15: CLOSED | G15: ROUTINE | H15: 45604 | I15: KATHERINE HETTER | J15: HERBICIDE | K15: TRUE | L15: =SUBSTITUTE(LOWER(SUBSTITUTE(SUBSTITUTE(SUBSTITUTE(B15," ",""),"/",""),"&","")),"and","") -> reglonedesiccant | M15: =_xlfn.CONCAT(L15,A15) -> reglonedesiccant100-1061 | N15: =IFERROR(VLOOKUP(LOWER(M15),file_list!$B:$B,1,FALSE),FALSE) -> reglonedesiccant100-1061 | O15: =IF(N15=FALSE,"FALSE","TRUE") -> TRUE
A16: 100-1063 | B16: REWARD MANUFACTURING CONCENTRATE | C16: 100 | D16: REGISTERED | E16: 1288082 | F16: CLOSED | G16: ROUTINE | H16: 45604 | I16: KATHERINE HETTER | J16: HERBICIDE | K16: TRUE | L16: =SUBSTITUTE(LOWER(SUBSTITUTE(SUBSTITUTE(SUBSTITUTE(B16," ",""),"/",""),"&","")),"and","") -> rewardmanufacturingconcentrate | M16: =_xlfn.CONCAT(L16,A16) -> rewardmanufacturingconcentrate100-1063 | N16: =IFERROR(VLOOKUP(LOWER(M16),file_list!$B:$B,1,FALSE),FALSE) -> rewardmanufacturingconcentrate100-1063 | O16: =IF(N16=FALSE,"FALSE","TRUE") -> TRUE
A17: 100-1066 | B17: DEMAND CS INSECTICIDE (NO USE WITHIN 100 FT. OF COASTAL MARSHES) (2ee - brown marmorated stink bug/kudzu stink bug) | C17: 100 | D17: REGISTERED | E17: 1197077 | F17: CLOSED | G17: 2EE | H17: 43983 | I17: SHAUN PETERSON | J17: INSECTICIDE | K17: FALSE | L17: =SUBSTITUTE(LOWER(SUBSTITUTE(SUBSTITUTE(SUBSTITUTE(B17," ",""),"/",""),"&","")),"and","") -> demcsinsecticide(nousewithin100ft.ofcoastalmarshes)(2ee-brownmarmoratedstinkbugkudzustinkbug) | M17: =_xlfn.CONCAT(L17,A17) -> demcsinsecticide(nousewithin100ft.ofcoastalmarshes)(2ee-brownmarmoratedstinkbugkudzustinkbug)100-1066 | N17: =IFERROR(VLOOKUP(LOWER(M17),file_list!$B:$B,1,FALSE),FALSE) -> demcsinsecticide(nousewithin100ft.ofcoastalmarshes)(2ee-brownmarmoratedstinkbugkudzustinkbug)100-1066 | O17: =IF(N17=FALSE,"FALSE","TRUE") -> TRUE
A18: 100-1066 | B18: DEMAND CS INSECTICIDE (NO USE WITHIN 100 FT. OF COASTAL MARSHES) | C18: 100 | D18: REGISTERED | E18: 1288082 | F18: CLOSED | G18: ROUTINE | H18: 45604 | I18: KATHERINE HETTER | J18: INSECTICIDE | K18: TRUE | L18: =SUBSTITUTE(LOWER(SUBSTITUTE(SUBSTITUTE(SUBSTITUTE(B18," ",""),"/",""),"&","")),"and","") -> demcsinsecticide(nousewithin100ft.ofcoastalmarshes) | M18: =_xlfn.CONCAT(L18,A18) -> demcsinsecticide(nousewithin100ft.ofcoastalmarshes)100-1066 | N18: =IFERROR(VLOOKUP(LOWER(M18),file_list!$B:$B,1,FALSE),FALSE) -> demcsinsecticide(nousewithin100ft.ofcoastalmarshes)100-1066 | O18: =IF(N18=FALSE,"FALSE","TRUE") -> TRUE
A19: 100-1066 | B19: PATROL (2ee - Spotted Lanternfly) | C19: 100 | D19: REGISTERED | E19: 1220455 | F19: CLOSED | G19: 2EE | H19: 44327 | I19: SHAUN PETERSON | J19: INSECTICIDE | K19: TRUE | L19: =SUBSTITUTE(LOWER(SUBSTITUTE(SUBSTITUTE(SUBSTITUTE(B19," ",""),"/",""),"&","")),"and","") -> patrol(2ee-spottedlanternfly) | M19: =_xlfn.CONCAT(L19,A19) -> patrol(2ee-spottedlanternfly)100-1066 | N19: =IFERROR(VLOOKUP(LOWER(M19),file_list!$B:$B,1,FALSE),FALSE) -> patrol(2ee-spottedlanternfly)100-1066 | O19: =IF(N19=FALSE,"FALSE","TRUE") -> TRUE
A20: 100-1066 | B20: DEMAND CS INSECTICIDE (NO USE WITHIN 100 FT. OF COASTAL MARSHES) (2ee - spotted lanternfly) | C20: 100 | D20: REGISTERED | E20: 1189769 | F20: CLOSED | G20: 2EE | H20: 43859 | I20: SHAUN PETERSON | J20: INSECTICIDE | K20: TRUE | L20: =SUBSTITUTE(LOWER(SUBSTITUTE(SUBSTITUTE(SUBSTITUTE(B20," ",""),"/",""),"&","")),"and","") -> demcsinsecticide(nousewithin100ft.ofcoastalmarshes)(2ee-spottedlanternfly) | M20: =_xlfn.CONCAT(L20,A20) -> demcsinsecticide(nousewithin100ft.ofcoastalmarshes)(2ee-spottedlanternfly)100-1066 | N20: =IFERROR(VLOOKUP(LOWER(M20),file_list!$B:$B,1,FALSE),FALSE) -> demcsinsecticide(nousewithin100ft.ofcoastalmarshes)(2ee-spottedlanternfly)100-1066 | O20: =IF(N20=FALSE,"FALSE","TRUE") -> TRUE
A21: 100-1066 | B21: PATROL (NO USE WITHIN 100' OF COASTAL MARSHES IN NYS) (2EE - BROWN MARMORATED STINK BUG AND KUDZU STINK BUG) | C21: 100 | D21: REGISTERED | E21: 22512 | F21: CLOSED | G21: 2EE | H21: 40739 | J21: INSECTICIDE | K21: TRUE | L21: =SUBSTITUTE(LOWER(SUBSTITUTE(SUBSTITUTE(SUBSTITUTE(B21," ",""),"/",""),"&","")),"and","") -> patrol(nousewithin100'ofcoastalmarshesinnys)(2ee-brownmarmoratedstinkbugkudzustinkbug) | M21: =_xlfn.CONCAT(L21,A21) -> patrol(nousewithin100'ofcoastalmarshesinnys)(2ee-brownmarmoratedstinkbugkudzustinkbug)100-1066 | N21: =IFERROR(VLOOKUP(LOWER(M21),file_list!$B:$B,1,FALSE),FALSE) -> patrol(nousewithin100'ofcoastalmarshesinnys)(2ee-brownmarmoratedstinkbugkudzustinkbug)100-1066 | O21: =IF(N21=FALSE,"FALSE","TRUE") -> TRUE
A22: 100-1066 | B22: PATROL (NO USE WITHIN 100' OF COASTAL MARSHES IN NYS) | C22: 100 | D22: REGISTERED | E22: 1288082 | F22: CLOSED | G22: ROUTINE | H22: 45604 | I22: KATHERINE HETTER | J22: INSECTICIDE | K22: TRUE | L22: =SUBSTITUTE(LOWER(SUBSTITUTE(SUBSTITUTE(SUBSTITUTE(B22," ",""),"/",""),"&","")),"and","") -> patrol(nousewithin100'ofcoastalmarshesinnys) | M22: =_xlfn.CONCAT(L22,A22) -> patrol(nousewithin100'ofcoastalmarshesinnys)100-1066 | N22: =IFERROR(VLOOKUP(LOWER(M22),file_list!$B:$B,1,FALSE),FALSE) -> patrol(nousewithin100'ofcoastalmarshesinnys)100-1066 | O22: =IF(N22=FALSE,"FALSE","TRUE") -> TRUE
A23: 100-1066 | B23: BORDER (no app within 100 ft of coastal marsh in ny) | C23: 100 | D23: REGISTERED | E23: 1288082 | F23: CLOSED | G23: ROUTINE | H23: 45604 | I23: KATHERINE HETTER | J23: INSECTICIDE | K23: TRUE | L23: =SUBSTITUTE(LOWER(SUBSTITUTE(SUBSTITUTE(SUBSTITUTE(B23," ",""),"/",""),"&","")),"and","") -> border(noappwithin100ftofcoastalmarshinny) | M23: =_xlfn.CONCAT(L23,A23) -> border(noappwithin100ftofcoastalmarshinny)100-1066 | N23: =IFERROR(VLOOKUP(LOWER(M23),file_list!$B:$B,1,FALSE),FALSE) -> border(noappwithin100ftofcoastalmarshinny)100-1066 | O23: =IF(N23=FALSE,"FALSE","TRUE") -> TRUE
A24: 100-1070 | B24: FUSILADE DX HERBICIDE (NOT FOR SALE, USE, OR DISTRIBUTION IN NASSAU AND SUFFOLK COUNTIES) | C24: 100 | D24: REGISTERED | E24: 1301365 | F24: CLOSED | G24: ROUTINE | H24: 45813 | I24: MATTHEW J GOGIS | J24: HERBICIDE | K24: TRUE | L24: =SUBSTITUTE(LOWER(SUBSTITUTE(SUBSTITUTE(SUBSTITUTE(B24," ",""),"/",""),"&","")),"and","") -> fusiladedxherbicide(notforsale,use,ordistributioninnassausuffolkcounties) | M24: =_xlfn.CONCAT(L24,A24) -> fusiladedxherbicide(notforsale,use,ordistributioninnassausuffolkcounties)100-1070 | N24: =IFERROR(VLOOKUP(LOWER(M24),file_list!$B:$B,1,FALSE),FALSE) -> fusiladedxherbicide(notforsale,use,ordistributioninnassausuffolkcounties)100-1070 | O24: =IF(N24=FALSE,"FALSE","TRUE") -> TRUE
A25: 100-1075 | B25: FORCE 3G INSECTICIDE (NYS MAX RATE 0.164 LB AI/A/YR) | C25: 100 | D25: REGISTERED | E25: 1288082 | F25: CLOSED | G25: ROUTINE | H25: 45604 | I25: KATHERINE HETTER | J25: INSECTICIDE | K25: FALSE | L25: =SUBSTITUTE(LOWER(SUBSTITUTE(SUBSTITUTE(SUBSTITUTE(B25," ",""),"/",""),"&","")),"and","") -> force3ginsecticide(nysmaxrate0.164lbaiayr) | M25: =_xlfn.CONCAT(L25,A25) -> force3ginsecticide(nysmaxrate0.164lbaiayr)100-1075 | N25: =IFERROR(VLOOKUP(LOWER(M25),file_list!$B:$B,1,FALSE),FALSE) -> force3ginsecticide(nysmaxrate0.164lbaiayr)100-1075 | O25: =IF(N25=FALSE,"FALSE","TRUE") -> TRUE
A26: 100-1084 | B26: FUSILADE II TURF AND ORNAMENTAL HERBICIDE (UNRESTRICTED 7/25/16) | C26: 100 | D26: REGISTERED | E26: 1288082 | F26: CLOSED | G26: ROUTINE | H26: 45604 | I26: KATHERINE HETTER | J26: HERBICIDE | K26: FALSE | L26: =SUBSTITUTE(LOWER(SUBSTITUTE(SUBSTITUTE(SUBSTITUTE(B26," ",""),"/",""),"&","")),"and","") -> fusiladeiiturfornamentalherbicide(unrestricted72516) | M26: =_xlfn.CONCAT(L26,A26) -> fusiladeiiturfornamentalherbicide(unrestricted72516)100-1084 | N26: =IFERROR(VLOOKUP(LOWER(M26),file_list!$B:$B,1,FALSE),FALSE) -> fusiladeiiturfornamentalherbicide(unrestricted72516)100-1084 | O26: =IF(N26=FALSE,"FALSE","TRUE") -> TRUE
A27: 100-1088 | B27: SCIMITAR GC INSECTICIDE (NO USE WITHIN 100' OF COASTAL MARSHES) | C27: 100 | D27: REGISTERED | E27: 1288082 | F27: CLOSED | G27: ROUTINE | H27: 45604 | I27: KATHERINE HETTER | J27: INSECTICIDE | K27: TRUE | L27: =SUBSTITUTE(LOWER(SUBSTITUTE(SUBSTITUTE(SUBSTITUTE(B27," ",""),"/",""),"&","")),"and","") -> scimitargcinsecticide(nousewithin100'ofcoastalmarshes) | M27: =_xlfn.CONCAT(L27,A27) -> scimitargcinsecticide(nousewithin100'ofcoastalmarshes)100-1088 | N27: =IFERROR(VLOOKUP(LOWER(M27),file_list!$B:$B,1,FALSE),FALSE) -> scimitargcinsecticide(nousewithin100'ofcoastalmarshes)100-1088 | O27: =IF(N27=FALSE,"FALSE","TRUE") -> TRUE
A28: 100-1093 | B28: HERITAGE FUNGICIDE (2EE - BROWN RING PATCH & RHIZOCTONIA LEAF AND SHEATH SPOT) | C28: 100 | D28: REGISTERED | E28: 18585 | F28: CLOSED | G28: 2EE | H28: 40319 | J28: FUNGICIDE | K28: FALSE | L28: =SUBSTITUTE(LOWER(SUBSTITUTE(SUBSTITUTE(SUBSTITUTE(B28," ",""),"/",""),"&","")),"and","") -> heritagefungicide(2ee-brownringpatchrhizoctonialeafsheathspot) | M28: =_xlfn.CONCAT(L28,A28) -> heritagefungicide(2ee-brownringpatchrhizoctonialeafsheathspot)100-1093 | N28: =IFERROR(VLOOKUP(LOWER(M28),file_list!$B:$B,1,FALSE),FALSE) -> heritagefungicide(2ee-brownringpatchrhizoctonialeafsheathspot)100-1093 | O28: =IF(N28=FALSE,"FALSE","TRUE") -> TRUE
A29: 100-1093 | B29: HERITAGE FUNGICIDE (2EE - PYTHIUM ROOT DYSFUNCTION) | C29: 100 | D29: REGISTERED | E29: 28211 | F29: CLOSED | G29: 2EE | H29: 41352 | J29: FUNGICIDE | K29: TRUE | L29: =SUBSTITUTE(LOWER(SUBSTITUTE(SUBSTITUTE(SUBSTITUTE(B29," ",""),"/",""),"&","")),"and","") -> heritagefungicide(2ee-pythiumrootdysfunction) | M29: =_xlfn.CONCAT(L29,A29) -> heritagefungicide(2ee-pythiumrootdysfunction)100-1093 | N29: =IFERROR(VLOOKUP(LOWER(M29),file_list!$B:$B,1,FALSE),FALSE) -> heritagefungicide(2ee-pythiumrootdysfunction)100-1093 | O29: =IF(N29=FALSE,"FALSE","TRUE") -> TRUE
A30: 100-1093 | B30: HERITAGE FUNGICIDE | C30: 100 | D30: REGISTERED | E30: 1288082 | F30: CLOSED | G30: ROUTINE | H30: 45604 | I30: KATHERINE HETTER | J30: FUNGICIDE | K30: TRUE | L30: =SUBSTITUTE(LOWER(SUBSTITUTE(SUBSTITUTE(SUBSTITUTE(B30," ",""),"/",""),"&","")),"and","") -> heritagefungicide | M30: =_xlfn.CONCAT(L30,A30) -> heritagefungicide100-1093 | N30: =IFERROR(VLOOKUP(LOWER(M30),file_list!$B:$B,1,FALSE),FALSE) -> heritagefungicide100-1093 | O30: =IF(N30=FALSE,"FALSE","TRUE") -> TRUE
A31: 100-1093 | B31: HERITAGE FUNGICIDE (2EE - CERCOSPORA LEAF SPOT) | C31: 100 | D31: REGISTERED | E31: 22802 | F31: CLOSED | G31: 2EE | H31: 40764 | J31: FUNGICIDE | K31: TRUE | L31: =SUBSTITUTE(LOWER(SUBSTITUTE(SUBSTITUTE(SUBSTITUTE(B31," ",""),"/",""),"&","")),"and","") -> heritagefungicide(2ee-cercosporaleafspot) | M31: =_xlfn.CONCAT(L31,A31) -> heritagefungicide(2ee-cercosporaleafspot)100-1093 | N31: =IFERROR(VLOOKUP(LOWER(M31),file_list!$B:$B,1,FALSE),FALSE) -> heritagefungicide(2ee-cercosporaleafspot)100-1093 | O31: =IF(N31=FALSE,"FALSE","TRUE") -> TRUE
A32: 100-1093 | B32: HERITAGE FUNGICIDE (2EE - DOWNY MILDEW) | C32: 100 | D32: REGISTERED | E32: 24110 | F32: CLOSED | G32: 2EE | H32: 40927 | J32: FUNGICIDE | K32: TRUE | L32: =SUBSTITUTE(LOWER(SUBSTITUTE(SUBSTITUTE(SUBSTITUTE(B32," ",""),"/",""),"&","")),"and","") -> heritagefungicide(2ee-downymildew) | M32: =_xlfn.CONCAT(L32,A32) -> heritagefungicide(2ee-downymildew)100-1093 | N32: =IFERROR(VLOOKUP(LOWER(M32),file_list!$B:$B,1,FALSE),FALSE) -> heritagefungicide(2ee-downymildew)100-1093 | O32: =IF(N32=FALSE,"FALSE","TRUE") -> TRUE
A33: 100-1098 | B33: QUADRIS FLOWABLE FUNGICIDE (2EE - REDUCED RATES) | C33: 100 | D33: REGISTERED | E33: 6740 | F33: CLOSED | G33: 2EE | H33: 39043 | J33: FUNGICIDE | K33: TRUE | L33: =SUBSTITUTE(LOWER(SUBSTITUTE(SUBSTITUTE(SUBSTITUTE(B33," ",""),"/",""),"&","")),"and","") -> quadrisflowablefungicide(2ee-reducedrates) | M33: =_xlfn.CONCAT(L33,A33) -> quadrisflowablefungicide(2ee-reducedrates)100-1098 | N33: =IFERROR(VLOOKUP(LOWER(M33),file_list!$B:$B,1,FALSE),FALSE) -> quadrisflowablefungicide(2ee-reducedrates)100-1098 | O33: =IF(N33=FALSE,"FALSE","TRUE") -> TRUE
A34: 100-1098 | B34: ABOUND FLOWABLE FUNGICIDE | C34: 100 | D34: DISCONTINUED | E34: 1288082 | F34: CLOSED | G34: ROUTINE | H34: 45604 | I34: KATHERINE HETTER | J34: FUNGICIDE | K34: TRUE | L34: =SUBSTITUTE(LOWER(SUBSTITUTE(SUBSTITUTE(SUBSTITUTE(B34," ",""),"/",""),"&","")),"and","") -> aboundflowablefungicide | M34: =_xlfn.CONCAT(L34,A34) -> aboundflowablefungicide100-1098 | N34: =IFERROR(VLOOKUP(LOWER(M34),file_list!$B:$B,1,FALSE),FALSE) -> aboundflowablefungicide100-1098 | O34: =IF(N34=FALSE,"FALSE","TRUE") -> TRUE
A35: 100-1098 | B35: QUADRIS FLOWABLE FUNGICIDE | C35: 100 | D35: REGISTERED | E35: 1288082 | F35: CLOSED | G35: ROUTINE | H35: 45604 | I35: KATHERINE HETTER | J35: FUNGICIDE | K35: TRUE | L35: =SUBSTITUTE(LOWER(SUBSTITUTE(SUBSTITUTE(SUBSTITUTE(B35," ",""),"/",""),"&","")),"and","") -> quadrisflowablefungicide | M35: =_xlfn.CONCAT(L35,A35) -> quadrisflowablefungicide100-1098 | N35: =IFERROR(VLOOKUP(LOWER(M35),file_list!$B:$B,1,FALSE),FALSE) -> quadrisflowablefungicide100-1098 | O35: =IF(N35=FALSE,"FALSE","TRUE") -> TRUE
A36: 100-1098 | B36: AFRAME | C36: 100 | D36: REGISTERED | E36: 1288082 | F36: CLOSED | G36: ROUTINE | H36: 45604 | I36: KATHERINE HETTER | J36: FUNGICIDE | K36: TRUE | L36: =SUBSTITUTE(LOWER(SUBSTITUTE(SUBSTITUTE(SUBSTITUTE(B36," ",""),"/",""),"&","")),"and","") -> aframe | M36: =_xlfn.CONCAT(L36,A36) -> aframe100-1098 | N36: =IFERROR(VLOOKUP(LOWER(M36),file_list!$B:$B,1,FALSE),FALSE) -> aframe100-1098 | O36: =IF(N36=FALSE,"FALSE","TRUE") -> TRUE
A37: 100-1101 | B37: FLEXSTAR | C37: 100 | D37: REGISTERED | E37: 1288082 | F37: CLOSED | G37: ROUTINE | H37: 45604 | I37: KATHERINE HETTER | J37: HERBICIDE | K37: TRUE | L37: =SUBSTITUTE(LOWER(SUBSTITUTE(SUBSTITUTE(SUBSTITUTE(B37," ",""),"/",""),"&","")),"and","") -> flexstar | M37: =_xlfn.CONCAT(L37,A37) -> flexstar100-1101 | N37: =IFERROR(VLOOKUP(LOWER(M37),file_list!$B:$B,1,FALSE),FALSE) -> flexstar100-1101 | O37: =IF(N37=FALSE,"FALSE","TRUE") -> TRUE
A38: 100-1101 | B38: SEDONA | C38: 100 | D38: REGISTERED | E38: 1288082 | F38: CLOSED | G38: ROUTINE | H38: 45604 | I38: KATHERINE HETTER | J38: HERBICIDE | K38: TRUE | L38: =SUBSTITUTE(LOWER(SUBSTITUTE(SUBSTITUTE(SUBSTITUTE(B38," ",""),"/",""),"&","")),"and","") -> sedona | M38: =_xlfn.CONCAT(L38,A38) -> sedona100-1101 | N38: =IFERROR(VLOOKUP(LOWER(M38),file_list!$B:$B,1,FALSE),FALSE) -> sedona100-1101 | O38: =IF(N38=FALSE,"FALSE","TRUE") -> TRUE
A39: 100-1111 | B39: ARCHER INSECT GROWTH REGULATOR (RESTRICTED USE AS OF 3/7/16) | C39: 100 | D39: REGISTERED | E39: 1288082 | F39: CLOSED | G39: ROUTINE | H39: 45604 | I39: KATHERINE HETTER | J39: GROWTH REGULATOR, MOSQUITO LARVICIDE | K39: FALSE | L39: =SUBSTITUTE(LOWER(SUBSTITUTE(SUBSTITUTE(SUBSTITUTE(B39," ",""),"/",""),"&","")),"and","") -> archerinsectgrowthregulator(restricteduseasof3716) | M39: =_xlfn.CONCAT(L39,A39) -> archerinsectgrowthregulator(restricteduseasof3716)100-1111 | N39: =IFERROR(VLOOKUP(LOWER(M39),file_list!$B:$B,1,FALSE),FALSE) -> archerinsectgrowthregulator(restricteduseasof3716)100-1111 | O39: =IF(N39=FALSE,"FALSE","TRUE") -> TRUE
A40: 100-1131 | B40: EXPLORER HERBICIDE | C40: 100 | D40: REGISTERED | E40: 1288082 | F40: CLOSED | G40: ROUTINE | H40: 45604 | I40: KATHERINE HETTER | J40: HERBICIDE | K40: TRUE | L40: =SUBSTITUTE(LOWER(SUBSTITUTE(SUBSTITUTE(SUBSTITUTE(B40," ",""),"/",""),"&","")),"and","") -> explorerherbicide | M40: =_xlfn.CONCAT(L40,A40) -> explorerherbicide100-1131 | N40: =IFERROR(VLOOKUP(LOWER(M40),file_list!$B:$B,1,FALSE),FALSE) -> explorerherbicide100-1131 | O40: =IF(N40=FALSE,"FALSE","TRUE") -> TRUE
A41: 100-1131 | B41: CALLISTO HERBICIDE (2EE - TANK MIX) | C41: 100 | D41: REGISTERED | E41: 6740 | F41: CLOSED | G41: 2EE | H41: 39043 | J41: HERBICIDE | K41: TRUE | L41: =SUBSTITUTE(LOWER(SUBSTITUTE(SUBSTITUTE(SUBSTITUTE(B41," ",""),"/",""),"&","")),"and","") -> callistoherbicide(2ee-tankmix) | M41: =_xlfn.CONCAT(L41,A41) -> callistoherbicide(2ee-tankmix)100-1131 | N41: =IFERROR(VLOOKUP(LOWER(M41),file_list!$B:$B,1,FALSE),FALSE) -> callistoherbicide(2ee-tankmix)100-1131 | O41: =IF(N41=FALSE,"FALSE","TRUE") -> TRUE
A42: 100-1131 | B42: CALLISTO HERBICIDE | C42: 100 | D42: REGISTERED | E42: 1288082 | F42: CLOSED | G42: ROUTINE | H42: 45604 | I42: KATHERINE HETTER | J42: HERBICIDE | K42: TRUE | L42: =SUBSTITUTE(LOWER(SUBSTITUTE(SUBSTITUTE(SUBSTITUTE(B42," ",""),"/",""),"&","")),"and","") -> callistoherbicide | M42: =_xlfn.CONCAT(L42,A42) -> callistoherbicide100-1131 | N42: =IFERROR(VLOOKUP(LOWER(M42),file_list!$B:$B,1,FALSE),FALSE) -> callistoherbicide100-1131 | O42: =IF(N42=FALSE,"FALSE","TRUE") -> TRUE
A43: 100-1139 | B43: BARRICADE 4FL HERBICIDE (UNRESTRICTED 1/1/2015) | C43: 100 | D43: REGISTERED | E43: 1288082 | F43: CLOSED | G43: ROUTINE | H43: 45604 | I43: KATHERINE HETTER | J43: HERBICIDE | K43: FALSE | L43: =SUBSTITUTE(LOWER(SUBSTITUTE(SUBSTITUTE(SUBSTITUTE(B43," ",""),"/",""),"&","")),"and","") -> barricade4flherbicide(unrestricted112015) | M43: =_xlfn.CONCAT(L43,A43) -> barricade4flherbicide(unrestricted112015)100-1139 | N43: =IFERROR(VLOOKUP(LOWER(M43),file_list!$B:$B,1,FALSE),FALSE) -> barricade4flherbicide(unrestricted112015)100-1139 | O43: =IF(N43=FALSE,"FALSE","TRUE") -> TRUE
A44: 100-1139 | B44: RESOLUTE 4FL | C44: 100 | D44: REGISTERED | E44: 1288082 | F44: CLOSED | G44: ROUTINE | H44: 45604 | I44: KATHERINE HETTER | J44: HERBICIDE | K44: TRUE | L44: =SUBSTITUTE(LOWER(SUBSTITUTE(SUBSTITUTE(SUBSTITUTE(B44," ",""),"/",""),"&","")),"and","") -> resolute4fl | M44: =_xlfn.CONCAT(L44,A44) -> resolute4fl100-1139 | N44: =IFERROR(VLOOKUP(LOWER(M44),file_list!$B:$B,1,FALSE),FALSE) -> resolute4fl100-1139 | O44: =IF(N44=FALSE,"FALSE","TRUE") -> TRUE
A45: 100-1141 | B45: DIVIDEND EXTREME FUNGICIDE | C45: 100 | D45: REGISTERED | E45: 1288082 | F45: CLOSED | G45: ROUTINE | H45: 45604 | I45: KATHERINE HETTER | J45: FUNGICIDE | K45: TRUE | L45: =SUBSTITUTE(LOWER(SUBSTITUTE(SUBSTITUTE(SUBSTITUTE(B45," ",""),"/",""),"&","")),"and","") -> dividendextremefungicide | M45: =_xlfn.CONCAT(L45,A45) -> dividendextremefungicide100-1141 | N45: =IFERROR(VLOOKUP(LOWER(M45),file_list!$B:$B,1,FALSE),FALSE) -> dividendextremefungicide100-1141 | O45: =IF(N45=FALSE,"FALSE","TRUE") -> TRUE
A46: 100-1158 | B46: MAXIM MZ | C46: 100 | D46: REGISTERED | E46: 1288082 | F46: CLOSED | G46: ROUTINE | H46: 45604 | I46: KATHERINE HETTER | J46: FUNGICIDE | K46: TRUE | L46: =SUBSTITUTE(LOWER(SUBSTITUTE(SUBSTITUTE(SUBSTITUTE(B46," ",""),"/",""),"&","")),"and","") -> maximmz | M46: =_xlfn.CONCAT(L46,A46) -> maximmz100-1158 | N46: =IFERROR(VLOOKUP(LOWER(M46),file_list!$B:$B,1,FALSE),FALSE) -> maximmz100-1158 | O46: =IF(N46=FALSE,"FALSE","TRUE") -> TRUE
A47: 100-1159 | B47: DYNASTY | C47: 100 | D47: REGISTERED | E47: 1288082 | F47: CLOSED | G47: ROUTINE | H47: 45604 | I47: KATHERINE HETTER | J47: FUNGICIDE | K47: TRUE | L47: =SUBSTITUTE(LOWER(SUBSTITUTE(SUBSTITUTE(SUBSTITUTE(B47," ",""),"/",""),"&","")),"and","") -> dynasty | M47: =_xlfn.CONCAT(L47,A47) -> dynasty100-1159 | N47: =IFERROR(VLOOKUP(LOWER(M47),file_list!$B:$B,1,FALSE),FALSE) -> dynasty100-1159 | O47: =IF(N47=FALSE,"FALSE","TRUE") -> TRUE
A48: 100-1162 | B48: BOUNDARY 6.5EC HERBICIDE (NOT FOR SALE/USE/DIST ON LONG ISLAND) (RESTRICTED AS OF 1/1/2007) | C48: 100 | D48: REGISTERED | E48: 1288082 | F48: CLOSED | G48: ROUTINE | H48: 45604 | I48: KATHERINE HETTER | J48: HERBICIDE | K48: FALSE | L48: =SUBSTITUTE(LOWER(SUBSTITUTE(SUBSTITUTE(SUBSTITUTE(B48," ",""),"/",""),"&","")),"and","") -> boundary6.5echerbicide(notforsaleusedistonlongisl)(restrictedasof112007) | M48: =_xlfn.CONCAT(L48,A48) -> boundary6.5echerbicide(notforsaleusedistonlongisl)(restrictedasof112007)100-1162 | N48: =IFERROR(VLOOKUP(LOWER(M48),file_list!$B:$B,1,FALSE),FALSE) -> boundary6.5echerbicide(notforsaleusedistonlongisl)(restrictedasof112007)100-1162 | O48: =IF(N48=FALSE,"FALSE","TRUE") -> TRUE
A49: 100-1171 | B49: QUADRIS OPTI | C49: 100 | D49: REGISTERED | E49: 1288082 | F49: CLOSED | G49: ROUTINE | H49: 45604 | I49: KATHERINE HETTER | J49: FUNGICIDE | K49: TRUE | L49: =SUBSTITUTE(LOWER(SUBSTITUTE(SUBSTITUTE(SUBSTITUTE(B49," ",""),"/",""),"&","")),"and","") -> quadrisopti | M49: =_xlfn.CONCAT(L49,A49) -> quadrisopti100-1171 | N49: =IFERROR(VLOOKUP(LOWER(M49),file_list!$B:$B,1,FALSE),FALSE) -> quadrisopti100-1171 | O49: =IF(N49=FALSE,"FALSE","TRUE") -> TRUE
A50: 100-1185 | B50: SEQUENCE HERBICIDE (NO USE IN NASSAU & SUFFOLK COUNTIES) (RESTRICTED AS OF 1/1/2007) | C50: 100 | D50: REGISTERED | E50: 1290656 | F50: CLOSED | G50: ROUTINE | H50: 45618 | I50: JYOTHI MURUNDI | J50: HERBICIDE | K50: FALSE | L50: =SUBSTITUTE(LOWER(SUBSTITUTE(SUBSTITUTE(SUBSTITUTE(B50," ",""),"/",""),"&","")),"and","") -> sequenceherbicide(nouseinnassausuffolkcounties)(restrictedasof112007) | M50: =_xlfn.CONCAT(L50,A50) -> sequenceherbicide(nouseinnassausuffolkcounties)(restrictedasof112007)100-1185 | N50: =IFERROR(VLOOKUP(LOWER(M50),file_list!$B:$B,1,FALSE),FALSE) -> sequenceherbicide(nouseinnassausuffolkcounties)(restrictedasof112007)100-1185 | O50: =IF(N50=FALSE,"FALSE","TRUE") -> TRUE
A51: 100-1187 | B51: UNIFORM | C51: 100 | D51: REGISTERED | E51: 1288082 | F51: CLOSED | G51: ROUTINE | H51: 45604 | I51: KATHERINE HETTER | J51: FUNGICIDE | K51: TRUE | L51: =SUBSTITUTE(LOWER(SUBSTITUTE(SUBSTITUTE(SUBSTITUTE(B51," ",""),"/",""),"&","")),"and","") -> uniform | M51: =_xlfn.CONCAT(L51,A51) -> uniform100-1187 | N51: =IFERROR(VLOOKUP(LOWER(M51),file_list!$B:$B,1,FALSE),FALSE) -> uniform100-1187 | O51: =IF(N51=FALSE,"FALSE","TRUE") -> TRUE
A52: 100-1191 | B52: HERITAGE TL (2EE - BROWN RING PATCH) | C52: 100 | D52: REGISTERED | E52: 18585 | F52: CLOSED | G52: 2EE | H52: 40319 | J52: FUNGICIDE | K52: TRUE | L52: =SUBSTITUTE(LOWER(SUBSTITUTE(SUBSTITUTE(SUBSTITUTE(B52," ",""),"/",""),"&","")),"and","") -> heritagetl(2ee-brownringpatch) | M52: =_xlfn.CONCAT(L52,A52) -> heritagetl(2ee-brownringpatch)100-1191 | N52: =IFERROR(VLOOKUP(LOWER(M52),file_list!$B:$B,1,FALSE),FALSE) -> heritagetl(2ee-brownringpatch)100-1191 | O52: =IF(N52=FALSE,"FALSE","TRUE") -> TRUE
A53: 100-1191 | B53: HERITAGE TL (2EE - PYTHIUM ROOT DYSFUNCTION) | C53: 100 | D53: REGISTERED | E53: 28211 | F53: CLOSED | G53: 2EE | H53: 41352 | J53: FUNGICIDE | K53: TRUE | L53: =SUBSTITUTE(LOWER(SUBSTITUTE(SUBSTITUTE(SUBSTITUTE(B53," ",""),"/",""),"&","")),"and","") -> heritagetl(2ee-pythiumrootdysfunction) | M53: =_xlfn.CONCAT(L53,A53) -> heritagetl(2ee-pythiumrootdysfunction)100-1191 | N53: =IFERROR(VLOOKUP(LOWER(M53),file_list!$B:$B,1,FALSE),FALSE) -> heritagetl(2ee-pythiumrootdysfunction)100-1191 | O53: =IF(N53=FALSE,"FALSE","TRUE") -> TRUE
A54: 100-1191 | B54: HERITAGE TL | C54: 100 | D54: REGISTERED | E54: 1288082 | F54: CLOSED | G54: ROUTINE | H54: 45604 | I54: KATHERINE HETTER | J54: FUNGICIDE | K54: TRUE | L54: =SUBSTITUTE(LOWER(SUBSTITUTE(SUBSTITUTE(SUBSTITUTE(B54," ",""),"/",""),"&","")),"and","") -> heritagetl | M54: =_xlfn.CONCAT(L54,A54) -> heritagetl100-1191 | N54: =IFERROR(VLOOKUP(LOWER(M54),file_list!$B:$B,1,FALSE),FALSE) -> heritagetl100-1191 | O54: =IF(N54=FALSE,"FALSE","TRUE") -> TRUE
A55: 100-1195 | B55: APRONMAXX RFC | C55: 100 | D55: REGISTERED | E55: 1288082 | F55: CLOSED | G55: ROUTINE | H55: 45604 | I55: KATHERINE HETTER | J55: FUNGICIDE | K55: TRUE | L55: =SUBSTITUTE(LOWER(SUBSTITUTE(SUBSTITUTE(SUBSTITUTE(B55," ",""),"/",""),"&","")),"and","") -> apronmaxxrfc | M55: =_xlfn.CONCAT(L55,A55) -> apronmaxxrfc100-1195 | N55: =IFERROR(VLOOKUP(LOWER(M55),file_list!$B:$B,1,FALSE),FALSE) -> apronmaxxrfc100-1195 | O55: =IF(N55=FALSE,"FALSE","TRUE") -> TRUE
A56: 100-1202 | B56: RIDOMIL GOLD SL | C56: 100 | D56: REGISTERED | E56: 1288082 | F56: CLOSED | G56: ROUTINE | H56: 45604 | I56: KATHERINE HETTER | J56: FUNGICIDE | K56: TRUE | L56: =SUBSTITUTE(LOWER(SUBSTITUTE(SUBSTITUTE(SUBSTITUTE(B56," ",""),"/",""),"&","")),"and","") -> ridomilgoldsl | M56: =_xlfn.CONCAT(L56,A56) -> ridomilgoldsl100-1202 | N56: =IFERROR(VLOOKUP(LOWER(M56),file_list!$B:$B,1,FALSE),FALSE) -> ridomilgoldsl100-1202 | O56: =IF(N56=FALSE,"FALSE","TRUE") -> TRUE
A57: 100-1202 | B57: ORONDIS GOLD B | C57: 100 | D57: REGISTERED | E57: 1288082 | F57: CLOSED | G57: ROUTINE | H57: 45604 | I57: KATHERINE HETTER | J57: FUNGICIDE | K57: TRUE | L57: =SUBSTITUTE(LOWER(SUBSTITUTE(SUBSTITUTE(SUBSTITUTE(B57," ",""),"/",""),"&","")),"and","") -> orondisgoldb | M57: =_xlfn.CONCAT(L57,A57) -> orondisgoldb100-1202 | N57: =IFERROR(VLOOKUP(LOWER(M57),file_list!$B:$B,1,FALSE),FALSE) -> orondisgoldb100-1202 | O57: =IF(N57=FALSE,"FALSE","TRUE") -> TRUE
A58: 100-1216 | B58: HEADWAY | C58: 100 | D58: REGISTERED | E58: 1288082 | F58: CLOSED | G58: ROUTINE | H58: 45604 | I58: KATHERINE HETTER | J58: FUNGICIDE | K58: TRUE | L58: =SUBSTITUTE(LOWER(SUBSTITUTE(SUBSTITUTE(SUBSTITUTE(B58," ",""),"/",""),"&","")),"and","") -> headway | M58: =_xlfn.CONCAT(L58,A58) -> headway100-1216 | N58: =IFERROR(VLOOKUP(LOWER(M58),file_list!$B:$B,1,FALSE),FALSE) -> headway100-1216 | O58: =IF(N58=FALSE,"FALSE","TRUE") -> TRUE
A59: 100-1216 | B59: HEADWAY (2EE - BROWN RING PATCH) | C59: 100 | D59: REGISTERED | E59: 19256 | F59: CLOSED | G59: 2EE | H59: 40387 | J59: FUNGICIDE | K59: TRUE | L59: =SUBSTITUTE(LOWER(SUBSTITUTE(SUBSTITUTE(SUBSTITUTE(B59," ",""),"/",""),"&","")),"and","") -> headway(2ee-brownringpatch) | M59: =_xlfn.CONCAT(L59,A59) -> headway(2ee-brownringpatch)100-1216 | N59: =IFERROR(VLOOKUP(LOWER(M59),file_list!$B:$B,1,FALSE),FALSE) -> headway(2ee-brownringpatch)100-1216 | O59: =IF(N59=FALSE,"FALSE","TRUE") -> TRUE
A60: 100-1218 | B60: DEMON MAX | C60: 100 | D60: REGISTERED | E60: 1288082 | F60: CLOSED | G60: ROUTINE | H60: 45604 | I60: KATHERINE HETTER | J60: INSECTICIDE, TERMITICIDE | K60: TRUE | L60: =SUBSTITUTE(LOWER(SUBSTITUTE(SUBSTITUTE(SUBSTITUTE(B60," ",""),"/",""),"&","")),"and","") -> demonmax | M60: =_xlfn.CONCAT(L60,A60) -> demonmax100-1218 | N60: =IFERROR(VLOOKUP(LOWER(M60),file_list!$B:$B,1,FALSE),FALSE) -> demonmax100-1218 | O60: =IF(N60=FALSE,"FALSE","TRUE") -> TRUE
A61: 100-1221 | B61: RIDOMIL GOLD BRAVO SC | C61: 100 | D61: REGISTERED | E61: 1288082 | F61: CLOSED | G61: ROUTINE | H61: 45604 | I61: KATHERINE HETTER | J61: FUNGICIDE | K61: TRUE | L61: =SUBSTITUTE(LOWER(SUBSTITUTE(SUBSTITUTE(SUBSTITUTE(B61," ",""),"/",""),"&","")),"and","") -> ridomilgoldbravosc | M61: =_xlfn.CONCAT(L61,A61) -> ridomilgoldbravosc100-1221 | N61: =IFERROR(VLOOKUP(LOWER(M61),file_list!$B:$B,1,FALSE),FALSE) -> ridomilgoldbravosc100-1221 | O61: =IF(N61=FALSE,"FALSE","TRUE") -> TRUE
A62: 100-1226 | B62: ALTO 100 SL | C62: 100 | D62: REGISTERED | E62: 1288082 | F62: CLOSED | G62: ROUTINE | H62: 45604 | I62: KATHERINE HETTER | J62: FUNGICIDE | K62: TRUE | L62: =SUBSTITUTE(LOWER(SUBSTITUTE(SUBSTITUTE(SUBSTITUTE(B62," ",""),"/",""),"&","")),"and","") -> alto100sl | M62: =_xlfn.CONCAT(L62,A62) -> alto100sl100-1226 | N62: =IFERROR(VLOOKUP(LOWER(M62),file_list!$B:$B,1,FALSE),FALSE) -> alto100sl100-1226 | O62: =IF(N62=FALSE,"FALSE","TRUE") -> TRUE
A63: 100-1231 | B63: INSTRATA [MAXIMUM APPLICATION RATE ON LONG ISLAND 7 GALLONS/ACRE OR 20.5 FL. OZ. PER 1,000 SQ. FT.] | C63: 100 | D63: REGISTERED | E63: 1288082 | F63: CLOSED | G63: ROUTINE | H63: 45604 | I63: KATHERINE HETTER | J63: FUNGICIDE | K63: FALSE | L63: =SUBSTITUTE(LOWER(SUBSTITUTE(SUBSTITUTE(SUBSTITUTE(B63," ",""),"/",""),"&","")),"and","") -> instrata[maximumapplicationrateonlongisl7gallonsacreor20.5fl.oz.per1,000sq.ft.] | M63: =_xlfn.CONCAT(L63,A63) -> instrata[maximumapplicationrateonlongisl7gallonsacreor20.5fl.oz.per1,000sq.ft.]100-1231 | N63: =IFERROR(VLOOKUP(LOWER(M63),file_list!$B:$B,1,FALSE),FALSE) -> instrata[maximumapplicationrateonlongisl7gallonsacreor20.5fl.oz.per1,000sq.ft.]100-1231 | O63: =IF(N63=FALSE,"FALSE","TRUE") -> TRUE
A64: 100-1240 | B64: DEMAND G INSECTICIDE (DO NOT APPLY WITHIN 100FT OF COASTAL MARSH) | C64: 100 | D64: REGISTERED | E64: 1288082 | F64: CLOSED | G64: ROUTINE | H64: 45604 | I64: KATHERINE HETTER | J64: INSECTICIDE | K64: TRUE | L64: =SUBSTITUTE(LOWER(SUBSTITUTE(SUBSTITUTE(SUBSTITUTE(B64," ",""),"/",""),"&","")),"and","") -> demginsecticide(donotapplywithin100ftofcoastalmarsh) | M64: =_xlfn.CONCAT(L64,A64) -> demginsecticide(donotapplywithin100ftofcoastalmarsh)100-1240 | N64: =IFERROR(VLOOKUP(LOWER(M64),file_list!$B:$B,1,FALSE),FALSE) -> demginsecticide(donotapplywithin100ftofcoastalmarsh)100-1240 | O64: =IF(N64=FALSE,"FALSE","TRUE") -> TRUE
A65: 100-1242 | B65: SCHOLAR Max MP | C65: 100 | D65: REGISTERED | E65: 1288082 | F65: CLOSED | G65: ROUTINE | H65: 45604 | I65: KATHERINE HETTER | J65: FUNGICIDE | K65: TRUE | L65: =SUBSTITUTE(LOWER(SUBSTITUTE(SUBSTITUTE(SUBSTITUTE(B65," ",""),"/",""),"&","")),"and","") -> scholarmaxmp | M65: =_xlfn.CONCAT(L65,A65) -> scholarmaxmp100-1242 | N65: =IFERROR(VLOOKUP(LOWER(M65),file_list!$B:$B,1,FALSE),FALSE) -> scholarmaxmp100-1242 | O65: =IF(N65=FALSE,"FALSE","TRUE") -> TRUE
A66: 100-1242 | B66: SCHOLAR SC FUNGICIDE (2EE - ALTERNARIA ROT AND SURFACE MOLD) | C66: 100 | D66: REGISTERED | E66: 16414 | F66: CLOSED | G66: 2EE | H66: 40065 | J66: FUNGICIDE | K66: TRUE | L66: =SUBSTITUTE(LOWER(SUBSTITUTE(SUBSTITUTE(SUBSTITUTE(B66," ",""),"/",""),"&","")),"and","") -> scholarscfungicide(2ee-alternariarotsurfacemold) | M66: =_xlfn.CONCAT(L66,A66) -> scholarscfungicide(2ee-alternariarotsurfacemold)100-1242 | N66: =IFERROR(VLOOKUP(LOWER(M66),file_list!$B:$B,1,FALSE),FALSE) -> scholarscfungicide(2ee-alternariarotsurfacemold)100-1242 | O66: =IF(N66=FALSE,"FALSE","TRUE") -> TRUE
A67: 100-1242 | B67: SCHOLAR SC FUNGICIDE | C67: 100 | D67: REGISTERED | E67: 1288082 | F67: CLOSED | G67: ROUTINE | H67: 45604 | I67: KATHERINE HETTER | J67: FUNGICIDE | K67: TRUE | L67: =SUBSTITUTE(LOWER(SUBSTITUTE(SUBSTITUTE(SUBSTITUTE(B67," ",""),"/",""),"&","")),"and","") -> scholarscfungicide | M67: =_xlfn.CONCAT(L67,A67) -> scholarscfungicide100-1242 | N67: =IFERROR(VLOOKUP(LOWER(M67),file_list!$B:$B,1,FALSE),FALSE) -> scholarscfungicide100-1242 | O67: =IF(N67=FALSE,"FALSE","TRUE") -> TRUE
A68: 100-1248 | B68: CRUISERMAXX POTATO INSECTICIDE AND FUNGICIDE (NO NASSAU OR SUFFOLK - SELF-IMPOSED BY SYNGENTA) (RESTRICTED USE AS OF 1/1/2023) | C68: 100 | D68: REGISTERED | E68: 1288082 | F68: CLOSED | G68: ROUTINE | H68: 45604 | I68: KATHERINE HETTER | J68: FUNGICIDE, INSECTICIDE | K68: FALSE | L68: =SUBSTITUTE(LOWER(SUBSTITUTE(SUBSTITUTE(SUBSTITUTE(B68," ",""),"/",""),"&","")),"and","") -> cruisermaxxpotatoinsecticidefungicide(nonassauorsuffolk-self-imposedbysyngenta)(restricteduseasof112023) | M68: =_xlfn.CONCAT(L68,A68) -> cruisermaxxpotatoinsecticidefungicide(nonassauorsuffolk-self-imposedbysyngenta)(restricteduseasof112023)100-1248 | N68: =IFERROR(VLOOKUP(LOWER(M68),file_list!$B:$B,1,FALSE),FALSE) -> cruisermaxxpotatoinsecticidefungicide(nonassauorsuffolk-self-imposedbysyngenta)(restricteduseasof112023)100-1248 | O68: =IF(N68=FALSE,"FALSE","TRUE") -> TRUE
A69: 100-1254 | B69: REVUS FUNGICIDE | C69: 100 | D69: REGISTERED | E69: 1288082 | F69: CLOSED | G69: ROUTINE | H69: 45604 | I69: KATHERINE HETTER | J69: FUNGICIDE | K69: TRUE | L69: =SUBSTITUTE(LOWER(SUBSTITUTE(SUBSTITUTE(SUBSTITUTE(B69," ",""),"/",""),"&","")),"and","") -> revusfungicide | M69: =_xlfn.CONCAT(L69,A69) -> revusfungicide100-1254 | N69: =IFERROR(VLOOKUP(LOWER(M69),file_list!$B:$B,1,FALSE),FALSE) -> revusfungicide100-1254 | O69: =IF(N69=FALSE,"FALSE","TRUE") -> TRUE
A70: 100-1256 | B70: AXIAL XL HERBICIDE | C70: 100 | D70: REGISTERED | E70: 1288082 | F70: CLOSED | G70: ROUTINE | H70: 45604 | I70: KATHERINE HETTER | J70: HERBICIDE | K70: TRUE | L70: =SUBSTITUTE(LOWER(SUBSTITUTE(SUBSTITUTE(SUBSTITUTE(B70," ",""),"/",""),"&","")),"and","") -> axialxlherbicide | M70: =_xlfn.CONCAT(L70,A70) -> axialxlherbicide100-1256 | N70: =IFERROR(VLOOKUP(LOWER(M70),file_list!$B:$B,1,FALSE),FALSE) -> axialxlherbicide100-1256 | O70: =IF(N70=FALSE,"FALSE","TRUE") -> TRUE
A71: 100-1259 | B71: ABAMECTIN TECHNICAL II | C71: 100 | D71: REGISTERED | E71: 1288082 | F71: CLOSED | G71: ROUTINE | H71: 45604 | I71: KATHERINE HETTER | J71: INSECTICIDE, MITICIDE, NEMATICIDE | K71: TRUE | L71: =SUBSTITUTE(LOWER(SUBSTITUTE(SUBSTITUTE(SUBSTITUTE(B71," ",""),"/",""),"&","")),"and","") -> abamectintechnicalii | M71: =_xlfn.CONCAT(L71,A71) -> abamectintechnicalii100-1259 | N71: =IFERROR(VLOOKUP(LOWER(M71),file_list!$B:$B,1,FALSE),FALSE) -> abamectintechnicalii100-1259 | O71: =IF(N71=FALSE,"FALSE","TRUE") -> TRUE
A72: 100-1260 | B72: OPTIGARD ANT GEL BAIT | C72: 100 | D72: REGISTERED | E72: 1288082 | F72: CLOSED | G72: ROUTINE | H72: 45604 | I72: KATHERINE HETTER | J72: INSECTICIDE | K72: TRUE | L72: =SUBSTITUTE(LOWER(SUBSTITUTE(SUBSTITUTE(SUBSTITUTE(B72," ",""),"/",""),"&","")),"and","") -> optigardantgelbait | M72: =_xlfn.CONCAT(L72,A72) -> optigardantgelbait100-1260 | N72: =IFERROR(VLOOKUP(LOWER(M72),file_list!$B:$B,1,FALSE),FALSE) -> optigardantgelbait100-1260 | O72: =IF(N72=FALSE,"FALSE","TRUE") -> TRUE
A73: 100-1267 | B73: TENACITY | C73: 100 | D73: REGISTERED | E73: 1288082 | F73: CLOSED | G73: ROUTINE | H73: 45604 | I73: KATHERINE HETTER | J73: HERBICIDE | K73: TRUE | L73: =SUBSTITUTE(LOWER(SUBSTITUTE(SUBSTITUTE(SUBSTITUTE(B73," ",""),"/",""),"&","")),"and","") -> tenacity | M73: =_xlfn.CONCAT(L73,A73) -> tenacity100-1267 | N73: =IFERROR(VLOOKUP(LOWER(M73),file_list!$B:$B,1,FALSE),FALSE) -> tenacity100-1267 | O73: =IF(N73=FALSE,"FALSE","TRUE") -> TRUE
A74: 100-1268 | B74: PREFIX HERBICIDE (NOT FOR USE IN NASSAU / SUFFOLK COUNTIES) | C74: 100 | D74: REGISTERED | E74: 1295227 | F74: CLOSED | G74: ROUTINE | H74: 45712 | I74: MATTHEW J GOGIS | J74: HERBICIDE | K74: FALSE | L74: =SUBSTITUTE(LOWER(SUBSTITUTE(SUBSTITUTE(SUBSTITUTE(B74," ",""),"/",""),"&","")),"and","") -> prefixherbicide(notforuseinnassausuffolkcounties) | M74: =_xlfn.CONCAT(L74,A74) -> prefixherbicide(notforuseinnassausuffolkcounties)100-1268 | N74: =IFERROR(VLOOKUP(LOWER(M74),file_list!$B:$B,1,FALSE),FALSE) -> prefixherbicide(notforuseinnassausuffolkcounties)100-1268 | O74: =IF(N74=FALSE,"FALSE","TRUE") -> TRUE
A75: 100-1269 | B75: RIDOMIL GOLD MZ WG | C75: 100 | D75: REGISTERED | E75: 1288082 | F75: CLOSED | G75: ROUTINE | H75: 45604 | I75: KATHERINE HETTER | J75: FUNGICIDE | K75: TRUE | L75: =SUBSTITUTE(LOWER(SUBSTITUTE(SUBSTITUTE(SUBSTITUTE(B75," ",""),"/",""),"&","")),"and","") -> ridomilgoldmzwg | M75: =_xlfn.CONCAT(L75,A75) -> ridomilgoldmzwg100-1269 | N75: =IFERROR(VLOOKUP(LOWER(M75),file_list!$B:$B,1,FALSE),FALSE) -> ridomilgoldmzwg100-1269 | O75: =IF(N75=FALSE,"FALSE","TRUE") -> TRUE
A76: 100-1276 | B76: ENDIGO ZC (NO LI) (NYS SPECIFIC LANGUAGE - USE RATE AND BUFFER ZONE) | C76: 100 | D76: REGISTERED | E76: 1305354 | F76: CLOSED | G76: ROUTINE | H76: 45884 | I76: KATHERINE HETTER | J76: INSECTICIDE | K76: TRUE | L76: =SUBSTITUTE(LOWER(SUBSTITUTE(SUBSTITUTE(SUBSTITUTE(B76," ",""),"/",""),"&","")),"and","") -> endigozc(noli)(nysspecificlanguage-useratebufferzone) | M76: =_xlfn.CONCAT(L76,A76) -> endigozc(noli)(nysspecificlanguage-useratebufferzone)100-1276 | N76: =IFERROR(VLOOKUP(LOWER(M76),file_list!$B:$B,1,FALSE),FALSE) -> endigozc(noli)(nysspecificlanguage-useratebufferzone)100-1276 | O76: =IF(N76=FALSE,"FALSE","TRUE") -> TRUE
A77: 100-1278 | B77: REVUS TOP | C77: 100 | D77: REGISTERED | E77: 1288082 | F77: CLOSED | G77: ROUTINE | H77: 45604 | I77: KATHERINE HETTER | J77: FUNGICIDE | K77: TRUE | L77: =SUBSTITUTE(LOWER(SUBSTITUTE(SUBSTITUTE(SUBSTITUTE(B77," ",""),"/",""),"&","")),"and","") -> revustop | M77: =_xlfn.CONCAT(L77,A77) -> revustop100-1278 | N77: =IFERROR(VLOOKUP(LOWER(M77),file_list!$B:$B,1,FALSE),FALSE) -> revustop100-1278 | O77: =IF(N77=FALSE,"FALSE","TRUE") -> TRUE
A78: 100-1282 | B78: KOBRIX GT (NO SALE, DISTRIBUTION OR USE IN NASSAU AND SUFFOLK COUNTIES) | C78: 100 | D78: REGISTERED | E78: 1298524 | F78: CLOSED | G78: ROUTINE | H78: 45762 | I78: MATTHEW J GOGIS | J78: HERBICIDE | K78: TRUE | L78: =SUBSTITUTE(LOWER(SUBSTITUTE(SUBSTITUTE(SUBSTITUTE(B78," ",""),"/",""),"&","")),"and","") -> kobrixgt(nosale,distributionoruseinnassausuffolkcounties) | M78: =_xlfn.CONCAT(L78,A78) -> kobrixgt(nosale,distributionoruseinnassausuffolkcounties)100-1282 | N78: =IFERROR(VLOOKUP(LOWER(M78),file_list!$B:$B,1,FALSE),FALSE) -> kobrixgt(nosale,distributionoruseinnassausuffolkcounties)100-1282 | O78: =IF(N78=FALSE,"FALSE","TRUE") -> TRUE
... A82: 100-1291 | B82: PLATINUM 75 SG INSECTICIDE (NO LI) (NY MAX USE RATE 0.188 LB AI/ACRE/YEAR) | C82: 100 | D82: REGISTERED | E82: 1288082 | F82: CLOSED | G82: ROUTINE | H82: 45604 | I82: KATHERINE HETTER | J82: INSECTICIDE | K82: FALSE | L82: =SUBSTITUTE(LOWER(SUBSTITUTE(SUBSTITUTE(SUBSTITUTE(B82," ",""),"/",""),"&","")),"and","") -> platinum75sginsecticide(noli)(nymaxuserate0.188lbaiacreyear) | M82: =_xlfn.CONCAT(L82,A82) -> platinum75sginsecticide(noli)(nymaxuserate0.188lbaiacreyear)100-1291 | N82: =IFERROR(VLOOKUP(LOWER(M82),file_list!$B:$B,1,FALSE),FALSE) -> platinum75sginsecticide(noli)(nymaxuserate0.188lbaiacreyear)100-1291 | O82: =IF(N82=FALSE,"FALSE","TRUE") -> TRUE
A83: 100-1295 | B83: WARRIOR II WITH ZEON TECHNOLOGY (25 FOOT BUFFER STRIP TO COASTAL MARSHES) (2EE - SWEDE MIDGE) | C83: 100 | D83: REGISTERED | E83: 30134 | F83: CLOSED | G83: 2EE | H83: 41576 | J83: INSECTICIDE | K83: TRUE | L83: =SUBSTITUTE(LOWER(SUBSTITUTE(SUBSTITUTE(SUBSTITUTE(B83," ",""),"/",""),"&","")),"and","") -> warrioriiwithzeontechnology(25footbufferstriptocoastalmarshes)(2ee-swedemidge) | M83: =_xlfn.CONCAT(L83,A83) -> warrioriiwithzeontechnology(25footbufferstriptocoastalmarshes)(2ee-swedemidge)100-1295 | N83: =IFERROR(VLOOKUP(LOWER(M83),file_list!$B:$B,1,FALSE),FALSE) -> warrioriiwithzeontechnology(25footbufferstriptocoastalmarshes)(2ee-swedemidge)100-1295 | O83: =IF(N83=FALSE,"FALSE","TRUE") -> TRUE
A84: 100-1295 | B84: LAMCAP II (25 FOOT BUFFER STRIP TO COASTAL MARSHES) | C84: 100 | D84: REGISTERED | E84: 1306908 | F84: CLOSED | G84: ROUTINE | H84: 45911 | I84: KATHERINE HETTER | J84: INSECTICIDE | K84: TRUE | L84: =SUBSTITUTE(LOWER(SUBSTITUTE(SUBSTITUTE(SUBSTITUTE(B84," ",""),"/",""),"&","")),"and","") -> lamcapii(25footbufferstriptocoastalmarshes) | M84: =_xlfn.CONCAT(L84,A84) -> lamcapii(25footbufferstriptocoastalmarshes)100-1295 | N84: =IFERROR(VLOOKUP(LOWER(M84),file_list!$B:$B,1,FALSE),FALSE) -> lamcapii(25footbufferstriptocoastalmarshes)100-1295 | O84: =IF(N84=FALSE,"FALSE","TRUE") -> TRUE
A85: 100-1295 | B85: WARRIOR II WITH ZEON TECHNOLOGY (25 FOOT BUFFER STRIP TO COASTAL MARSHES) | C85: 100 | D85: REGISTERED | E85: 1306909 | F85: CLOSED | G85: ROUTINE | H85: 45911 | I85: KATHERINE HETTER | J85: INSECTICIDE | K85: TRUE | L85: =SUBSTITUTE(LOWER(SUBSTITUTE(SUBSTITUTE(SUBSTITUTE(B85," ",""),"/",""),"&","")),"and","") -> warrioriiwithzeontechnology(25footbufferstriptocoastalmarshes) | M85: =_xlfn.CONCAT(L85,A85) -> warrioriiwithzeontechnology(25footbufferstriptocoastalmarshes)100-1295 | N85: =IFERROR(VLOOKUP(LOWER(M85),file_list!$B:$B,1,FALSE),FALSE) -> warrioriiwithzeontechnology(25footbufferstriptocoastalmarshes)100-1295 | O85: =IF(N85=FALSE,"FALSE","TRUE") -> TRUE
A86: 100-1308 | B86: Archive | C86: 100 | D86: REGISTERED | E86: 1302170 | F86: CLOSED | G86: ROUTINE | H86: 45828 | I86: MATTHEW J GOGIS | J86: FUNGICIDE | K86: TRUE | L86: =SUBSTITUTE(LOWER(SUBSTITUTE(SUBSTITUTE(SUBSTITUTE(B86," ",""),"/",""),"&","")),"and","") -> archive | M86: =_xlfn.CONCAT(L86,A86) -> archive100-1308 | N86: =IFERROR(VLOOKUP(LOWER(M86),file_list!$B:$B,1,FALSE),FALSE) -> archive100-1308 | O86: =IF(N86=FALSE,"FALSE","TRUE") -> TRUE
A87: 100-1311 | B87: QUADRIS RIDOMIL GOLD SL FUNGICDE | C87: 100 | D87: REGISTERED | E87: 1288082 | F87: CLOSED | G87: ROUTINE | H87: 45604 | I87: KATHERINE HETTER | J87: FUNGICIDE | K87: TRUE | L87: =SUBSTITUTE(LOWER(SUBSTITUTE(SUBSTITUTE(SUBSTITUTE(B87," ",""),"/",""),"&","")),"and","") -> quadrisridomilgoldslfungicde | M87: =_xlfn.CONCAT(L87,A87) -> quadrisridomilgoldslfungicde100-1311 | N87: =IFERROR(VLOOKUP(LOWER(M87),file_list!$B:$B,1,FALSE),FALSE) -> quadrisridomilgoldslfungicde100-1311 | O87: =IF(N87=FALSE,"FALSE","TRUE") -> TRUE
A88: 100-1313 | B88: Amistar top | C88: 100 | D88: REGISTERED | E88: 1288082 | F88: CLOSED | G88: ROUTINE | H88: 45604 | I88: KATHERINE HETTER | J88: FUNGICIDE | K88: TRUE | L88: =SUBSTITUTE(LOWER(SUBSTITUTE(SUBSTITUTE(SUBSTITUTE(B88," ",""),"/",""),"&","")),"and","") -> amistartop | M88: =_xlfn.CONCAT(L88,A88) -> amistartop100-1313 | N88: =IFERROR(VLOOKUP(LOWER(M88),file_list!$B:$B,1,FALSE),FALSE) -> amistartop100-1313 | O88: =IF(N88=FALSE,"FALSE","TRUE") -> TRUE
A89: 100-1313 | B89: QUADRIS TOP FUNGICIDE | C89: 100 | D89: REGISTERED | E89: 1288082 | F89: CLOSED | G89: ROUTINE | H89: 45604 | I89: KATHERINE HETTER | J89: FUNGICIDE | K89: TRUE | L89: =SUBSTITUTE(LOWER(SUBSTITUTE(SUBSTITUTE(SUBSTITUTE(B89," ",""),"/",""),"&","")),"and","") -> quadristopfungicide | M89: =_xlfn.CONCAT(L89,A89) -> quadristopfungicide100-1313 | N89: =IFERROR(VLOOKUP(LOWER(M89),file_list!$B:$B,1,FALSE),FALSE) -> quadristopfungicide100-1313 | O89: =IF(N89=FALSE,"FALSE","TRUE") -> TRUE
A90: 100-1315 | B90: RENOWN FUNGICIDE | C90: 100 | D90: REGISTERED | E90: 1288082 | F90: CLOSED | G90: ROUTINE | H90: 45604 | I90: KATHERINE HETTER | J90: FUNGICIDE | K90: TRUE | L90: =SUBSTITUTE(LOWER(SUBSTITUTE(SUBSTITUTE(SUBSTITUTE(B90," ",""),"/",""),"&","")),"and","") -> renownfungicide | M90: =_xlfn.CONCAT(L90,A90) -> renownfungicide100-1315 | N90: =IFERROR(VLOOKUP(LOWER(M90),file_list!$B:$B,1,FALSE),FALSE) -> renownfungicide100-1315 | O90: =IF(N90=FALSE,"FALSE","TRUE") -> TRUE
A91: 100-1317 | B91: INSPIRE SUPER | C91: 100 | D91: REGISTERED | E91: 1288082 | F91: CLOSED | G91: ROUTINE | H91: 45604 | I91: KATHERINE HETTER | J91: FUNGICIDE | K91: TRUE | L91: =SUBSTITUTE(LOWER(SUBSTITUTE(SUBSTITUTE(SUBSTITUTE(B91," ",""),"/",""),"&","")),"and","") -> inspiresuper | M91: =_xlfn.CONCAT(L91,A91) -> inspiresuper100-1317 | N91: =IFERROR(VLOOKUP(LOWER(M91),file_list!$B:$B,1,FALSE),FALSE) -> inspiresuper100-1317 | O91: =IF(N91=FALSE,"FALSE","TRUE") -> TRUE
A92: 100-1318 | B92: DURIVO (NO SALE, USE. DISTRIBUTION IN NASSAU, SUFFOLK, KINGS, & QUEENS COUNTIES) (NYS BUFFER ZONES) | C92: 100 | D92: REGISTERED | E92: 1288082 | F92: CLOSED | G92: ROUTINE | H92: 45604 | I92: KATHERINE HETTER | J92: INSECTICIDE | K92: FALSE | L92: =SUBSTITUTE(LOWER(SUBSTITUTE(SUBSTITUTE(SUBSTITUTE(B92," ",""),"/",""),"&","")),"and","") -> durivo(nosale,use.distributioninnassau,suffolk,kings,queenscounties)(nysbufferzones) | M92: =_xlfn.CONCAT(L92,A92) -> durivo(nosale,use.distributioninnassau,suffolk,kings,queenscounties)(nysbufferzones)100-1318 | N92: =IFERROR(VLOOKUP(LOWER(M92),file_list!$B:$B,1,FALSE),FALSE) -> durivo(nosale,use.distributioninnassau,suffolk,kings,queenscounties)(nysbufferzones)100-1318 | O92: =IF(N92=FALSE,"FALSE","TRUE") -> TRUE
A93: 100-1319 | B93: VOLIAM FLEXI INSECTICIDE (NO LONG ISLAND, NO USE WITHIN 100 FEET OF WATER, NO AERIAL USE) (2EE - BROWN MARMORATED STINK BUG) | C93: 100 | D93: REGISTERED | E93: 29647 | F93: CLOSED | G93: 2EE | H93: 41352 | J93: INSECTICIDE | K93: TRUE | L93: =SUBSTITUTE(LOWER(SUBSTITUTE(SUBSTITUTE(SUBSTITUTE(B93," ",""),"/",""),"&","")),"and","") -> voliamflexiinsecticide(nolongisl,nousewithin100feetofwater,noaerialuse)(2ee-brownmarmoratedstinkbug) | M93: =_xlfn.CONCAT(L93,A93) -> voliamflexiinsecticide(nolongisl,nousewithin100feetofwater,noaerialuse)(2ee-brownmarmoratedstinkbug)100-1319 | N93: =IFERROR(VLOOKUP(LOWER(M93),file_list!$B:$B,1,FALSE),FALSE) -> voliamflexiinsecticide(nolongisl,nousewithin100feetofwater,noaerialuse)(2ee-brownmarmoratedstinkbug)100-1319 | O93: =IF(N93=FALSE,"FALSE","TRUE") -> TRUE
A94: 100-1319 | B94: VOLIAM FLEXI (NO Li Use) (NO USE WITHIN 100 FEET OF WATER) (NO AERIAL USE) | C94: 100 | D94: REGISTERED | E94: 1288082 | F94: CLOSED | G94: ROUTINE | H94: 45604 | I94: KATHERINE HETTER | J94: INSECTICIDE | K94: TRUE | L94: =SUBSTITUTE(LOWER(SUBSTITUTE(SUBSTITUTE(SUBSTITUTE(B94," ",""),"/",""),"&","")),"and","") -> voliamflexi(noliuse)(nousewithin100feetofwater)(noaerialuse) | M94: =_xlfn.CONCAT(L94,A94) -> voliamflexi(noliuse)(nousewithin100feetofwater)(noaerialuse)100-1319 | N94: =IFERROR(VLOOKUP(LOWER(M94),file_list!$B:$B,1,FALSE),FALSE) -> voliamflexi(noliuse)(nousewithin100feetofwater)(noaerialuse)100-1319 | O94: =IF(N94=FALSE,"FALSE","TRUE") -> TRUE
A95: 100-1323 | B95: HERITAGE G | C95: 100 | D95: REGISTERED | E95: 1288082 | F95: CLOSED | G95: ROUTINE | H95: 45604 | I95: KATHERINE HETTER | J95: FUNGICIDE | K95: TRUE | L95: =SUBSTITUTE(LOWER(SUBSTITUTE(SUBSTITUTE(SUBSTITUTE(B95," ",""),"/",""),"&","")),"and","") -> heritageg | M95: =_xlfn.CONCAT(L95,A95) -> heritageg100-1323 | N95: =IFERROR(VLOOKUP(LOWER(M95),file_list!$B:$B,1,FALSE),FALSE) -> heritageg100-1323 | O95: =IF(N95=FALSE,"FALSE","TRUE") -> TRUE
A96: 100-1324 | B96: QUILT XCEL FUNGICIDE | C96: 100 | D96: REGISTERED | E96: 1288082 | F96: CLOSED | G96: ROUTINE | H96: 45604 | I96: KATHERINE HETTER | J96: FUNGICIDE | K96: TRUE | L96: =SUBSTITUTE(LOWER(SUBSTITUTE(SUBSTITUTE(SUBSTITUTE(B96," ",""),"/",""),"&","")),"and","") -> quiltxcelfungicide | M96: =_xlfn.CONCAT(L96,A96) -> quiltxcelfungicide100-1324 | N96: =IFERROR(VLOOKUP(LOWER(M96),file_list!$B:$B,1,FALSE),FALSE) -> quiltxcelfungicide100-1324 | O96: =IF(N96=FALSE,"FALSE","TRUE") -> TRUE
A97: 100-1324 | B97: AFRAME PLUS | C97: 100 | D97: REGISTERED | E97: 1288082 | F97: CLOSED | G97: ROUTINE | H97: 45604 | I97: KATHERINE HETTER | J97: FUNGICIDE | K97: TRUE | L97: =SUBSTITUTE(LOWER(SUBSTITUTE(SUBSTITUTE(SUBSTITUTE(B97," ",""),"/",""),"&","")),"and","") -> aframeplus | M97: =_xlfn.CONCAT(L97,A97) -> aframeplus100-1324 | N97: =IFERROR(VLOOKUP(LOWER(M97),file_list!$B:$B,1,FALSE),FALSE) -> aframeplus100-1324 | O97: =IF(N97=FALSE,"FALSE","TRUE") -> TRUE
A98: 100-1326 | B98: BANNER MAXX II | C98: 100 | D98: REGISTERED | E98: 1288082 | F98: CLOSED | G98: ROUTINE | H98: 45604 | I98: KATHERINE HETTER | J98: FUNGICIDE | K98: TRUE | L98: =SUBSTITUTE(LOWER(SUBSTITUTE(SUBSTITUTE(SUBSTITUTE(B98," ",""),"/",""),"&","")),"and","") -> bannermaxxii | M98: =_xlfn.CONCAT(L98,A98) -> bannermaxxii100-1326 | N98: =IFERROR(VLOOKUP(LOWER(M98),file_list!$B:$B,1,FALSE),FALSE) -> bannermaxxii100-1326 | O98: =IF(N98=FALSE,"FALSE","TRUE") -> TRUE
A99: 100-1326 | B99: BANNER MAXX II (2EE - BROWN RING PATCH & RHIZOCTONIA LEAF AND SHEATH SPOT) | C99: 100 | D99: REGISTERED | E99: 18777 | F99: CLOSED | G99: 2EE | H99: 40340 | J99: FUNGICIDE | K99: FALSE | L99: =SUBSTITUTE(LOWER(SUBSTITUTE(SUBSTITUTE(SUBSTITUTE(B99," ",""),"/",""),"&","")),"and","") -> bannermaxxii(2ee-brownringpatchrhizoctonialeafsheathspot) | M99: =_xlfn.CONCAT(L99,A99) -> bannermaxxii(2ee-brownringpatchrhizoctonialeafsheathspot)100-1326 | N99: =IFERROR(VLOOKUP(LOWER(M99),file_list!$B:$B,1,FALSE),FALSE) -> bannermaxxii(2ee-brownringpatchrhizoctonialeafsheathspot)100-1326 | O99: =IF(N99=FALSE,"FALSE","TRUE") -> TRUE
A100: 100-1328 | B100: PALLADIUM (IN NASSAU & SUFFOLK COUNTIES IN NYS, USE LIMITED TO ORNAMENTALS IN GREENHOUSES, LATH, AND SHADEHOUSES) [RESTRICTED USE AS OF 12/31/2015] | C100: 100 | D100: REGISTERED | E100: 1288082 | F100: CLOSED | G100: ROUTINE | H100: 45604 | I100: KATHERINE HETTER | J100: FUNGICIDE | K100: FALSE | L100: =SUBSTITUTE(LOWER(SUBSTITUTE(SUBSTITUTE(SUBSTITUTE(B100," ",""),"/",""),"&","")),"and","") -> palladium(innassausuffolkcountiesinnys,uselimitedtoornamentalsingreenhouses,lath,shadehouses)[restricteduseasof12312015] | M100: =_xlfn.CONCAT(L100,A100) -> palladium(innassausuffolkcountiesinnys,uselimitedtoornamentalsingreenhouses,lath,shadehouses)[restricteduseasof12312015]100-1328 | N100: =IFERROR(VLOOKUP(LOWER(M100),file_list!$B:$B,1,FALSE),FALSE) -> palladium(innassausuffolkcountiesinnys,uselimitedtoornamentalsingreenhouses,lath,shadehouses)[restricteduseasof12312015]100-1328 | O100: =IF(N100=FALSE,"FALSE","TRUE") -> TRUE
A101: 100-1347 | B101: CONCERT II | C101: 100 | D101: REGISTERED | E101: 1288082 | F101: CLOSED | G101: ROUTINE | H101: 45604 | I101: KATHERINE HETTER | J101: FUNGICIDE | K101: TRUE | L101: =SUBSTITUTE(LOWER(SUBSTITUTE(SUBSTITUTE(SUBSTITUTE(B101," ",""),"/",""),"&","")),"and","") -> concertii | M101: =_xlfn.CONCAT(L101,A101) -> concertii100-1347 | N101: =IFERROR(VLOOKUP(LOWER(M101),file_list!$B:$B,1,FALSE),FALSE) -> concertii100-1347 | O101: =IF(N101=FALSE,"FALSE","TRUE") -> TRUE
A102: 100-1347 | B102: CONCERT II (FUNGICIDE) (2EE - BROWN RING PATCH) | C102: 100 | D102: REGISTERED | E102: 21821 | F102: CLOSED | G102: 2EE | H102: 40651 | J102: FUNGICIDE | K102: TRUE | L102: =SUBSTITUTE(LOWER(SUBSTITUTE(SUBSTITUTE(SUBSTITUTE(B102," ",""),"/",""),"&","")),"and","") -> concertii(fungicide)(2ee-brownringpatch) | M102: =_xlfn.CONCAT(L102,A102) -> concertii(fungicide)(2ee-brownringpatch)100-1347 | N102: =IFERROR(VLOOKUP(LOWER(M102),file_list!$B:$B,1,FALSE),FALSE) -> concertii(fungicide)(2ee-brownringpatch)100-1347 | O102: =IF(N102=FALSE,"FALSE","TRUE") -> TRUE
A103: 100-1350 | B103: AGRI-FLEX MITICIDE/INSECTICIDE (NO LI) (NYS MAX RATE 0.172 LB AI/A ON POME FRUIT) (NO AERIAL APP IN NY) | C103: 100 | D103: REGISTERED | E103: 1288082 | F103: CLOSED | G103: ROUTINE | H103: 45604 | I103: KATHERINE HETTER | J103: INSECTICIDE, MITICIDE | K103: FALSE | L103: =SUBSTITUTE(LOWER(SUBSTITUTE(SUBSTITUTE(SUBSTITUTE(B103," ",""),"/",""),"&","")),"and","") -> agri-flexmiticideinsecticide(noli)(nysmaxrate0.172lbaiaonpomefruit)(noaerialappinny) | M103: =_xlfn.CONCAT(L103,A103) -> agri-flexmiticideinsecticide(noli)(nysmaxrate0.172lbaiaonpomefruit)(noaerialappinny)100-1350 | N103: =IFERROR(VLOOKUP(LOWER(M103),file_list!$B:$B,1,FALSE),FALSE) -> agri-flexmiticideinsecticide(noli)(nysmaxrate0.172lbaiaonpomefruit)(noaerialappinny)100-1350 | O103: =IF(N103=FALSE,"FALSE","TRUE") -> TRUE
...

Sheet Sheet2
A1: I found that the download script that makes the current products edited was not giving accurate
A2: is_PDF_downloaded
A3: true false
A4: a lot were false that were actually downloaded
A5: this was because the files had clean names but the lookup did not, so I made a few columns that substituted special characters to get it to lookup and give a correct true false

Sheet file_list
A1: File_Name | B1: Lower
A2: BIOGUARDMAINTAINBURNOUT35185-503 | B2: =SUBSTITUTE(LOWER(A2),"and","") -> bioguardmaintainburnout35185-503
A3: ProvectaAdvancedFORDOGS(5-10lbs)91384-3 | B3: =SUBSTITUTE(LOWER(A3),"and","") -> provectaadvancedfordogs(5-10lbs)91384-3
A4: SUPERSHOCK48520-20005 | B4: =SUBSTITUTE(LOWER(A4),"and","") -> supershock48520-20005
A5: PROKLEANRESTOREL87508-3-104210 | B5: =SUBSTITUTE(LOWER(A5),"and","") -> prokleanrestorel87508-3-104210
A6: lalguardm52gr64137-31 | B6: =SUBSTITUTE(LOWER(A6),"and","") -> lalguardm52gr64137-31
A7: PATHWAYHERBICIDE(NOSALE,USE,ORDISTRIBUTIONINLI)(RESTRICTED2407)62719-31 | B7: =SUBSTITUTE(LOWER(A7),"and","") -> pathwayherbicide(nosale,use,ordistributioninli)(restricted2407)62719-31
A8: ADVANTAGEXDSMALLCAT72642-11 | B8: =SUBSTITUTE(LOWER(A8),"and","") -> advantagexdsmallcat72642-11
A9: VECTOBACWDGBIOLOGICALLARVICIDE73049-56 | B9: =SUBSTITUTE(LOWER(A9),"and","") -> vectobacwdgbiologicallarvicide73049-56
A10: VARROXSAN94413-3 | B10: =SUBSTITUTE(LOWER(A10),"and","") -> varroxsan94413-3
A11: PRO-MIXhpoBIOFUNGICIDE+MYCORRHIZAE74267-8 | B11: =SUBSTITUTE(LOWER(A11),"and","") -> pro-mixhpobiofungicide+mycorrhizae74267-8
A12: LysolBrandKills99.9%ofVirusesandBacteriaDailyCleanser777-131 | B12: =SUBSTITUTE(LOWER(A12),"and","") -> lysolbrkills99.9%ofvirusesbacteriadailycleanser777-131
A13: ANUEW1001-91 | B13: =SUBSTITUTE(LOWER(A13),"and","") -> anuew1001-91
... A10000: EMPYROS[nosale,distribution,oruseinnassauandsuffolkcounties,NY]5905-641 | B10000: =SUBSTITUTE(LOWER(A10000),"and","") -> empyros[nosale,distribution,oruseinnassausuffolkcounties,ny]5905-641
